ANDROID_BUILD.md
CMakeLists.txt
MANIFEST.in
README.md
buildozer.spec
pyproject.toml
setup.py
docs/API_REFERENCE.md
docs/GETTING_STARTED.md
docs/PYTHON_API.md
docs/PYTHON_BINDINGS_SUMMARY.md
examples/README.md
examples/platformer_example.py
examples/puzzle_example.py
examples/rpg_example.py
examples/shooter_example.py
examples/simple_game_example.py
include/pywrkgame/ai/AIFramework.h
include/pywrkgame/animation/AnimationSystem.h
include/pywrkgame/animation/IKSolver.h
include/pywrkgame/animation/ProceduralAnimation.h
include/pywrkgame/assets/AssetManager.h
include/pywrkgame/audio/AudioSystem.h
include/pywrkgame/core/ComponentManager.h
include/pywrkgame/core/EngineCore.h
include/pywrkgame/core/EntityManager.h
include/pywrkgame/core/PerformanceOptimizer.h
include/pywrkgame/core/SystemManager.h
include/pywrkgame/memory/MemoryManager.h
include/pywrkgame/network/NetworkManager.h
include/pywrkgame/physics/Box2DBackend.h
include/pywrkgame/physics/Bullet3Backend.h
include/pywrkgame/physics/PhysicsEngine.h
include/pywrkgame/physics/PhysicsMath.h
include/pywrkgame/platform/PlatformManager.h
include/pywrkgame/platform/TouchInputManager.h
include/pywrkgame/rendering/D3D12Device.h
include/pywrkgame/rendering/GlobalIllumination.h
include/pywrkgame/rendering/GraphicsDevice.h
include/pywrkgame/rendering/GraphicsTypes.h
include/pywrkgame/rendering/LODSystem.h
include/pywrkgame/rendering/MetalDevice.h
include/pywrkgame/rendering/PBRRenderer.h
include/pywrkgame/rendering/ParticleSystem.h
include/pywrkgame/rendering/PostProcessing.h
include/pywrkgame/rendering/RenderingEngine.h
include/pywrkgame/rendering/VulkanDevice.h
include/pywrkgame/tools/DebugTools.h
include/pywrkgame/tools/PerformanceProfiler.h
include/pywrkgame/ui/UISystem.h
python/CMakeLists.txt
python/__init__.py
python/audio_bindings.cpp
python/bindings.cpp
python/core_bindings.cpp
python/physics_bindings.cpp
python/pywrkgame_api.py
python/rendering_bindings.cpp
python/ui_bindings.cpp
src/CMakeLists.txt
src/ai/AIFramework.cpp
src/pywrkgame.egg-info/PKG-INFO
src/pywrkgame.egg-info/SOURCES.txt
src/pywrkgame.egg-info/dependency_links.txt
src/pywrkgame.egg-info/not-zip-safe
src/pywrkgame.egg-info/requires.txt
src/pywrkgame.egg-info/top_level.txt
