Metadata-Version: 2.4
Name: pywrkgame
Version: 3.0.3
Summary: High-performance game engine with Python bindings for 2D/3D games
Home-page: https://github.com/your-org/pywrkgame
Author: WorkerAI
Author-email: WorkerAI <workerai@mail.ru>
License: MIT
Project-URL: Homepage, https://github.com/your-org/pywrkgame
Project-URL: Documentation, https://github.com/your-org/pywrkgame/tree/main/docs
Project-URL: Repository, https://github.com/your-org/pywrkgame
Project-URL: Bug Tracker, https://github.com/your-org/pywrkgame/issues
Keywords: game,engine,gamedev,2d,3d,graphics,physics,audio,mobile,cross-platform
Classifier: Development Status :: 4 - Beta
Classifier: Intended Audience :: Developers
Classifier: Topic :: Games/Entertainment
Classifier: Topic :: Software Development :: Libraries :: Python Modules
Classifier: License :: OSI Approved :: MIT License
Classifier: Programming Language :: Python :: 3
Classifier: Programming Language :: Python :: 3.7
Classifier: Programming Language :: Python :: 3.8
Classifier: Programming Language :: Python :: 3.9
Classifier: Programming Language :: Python :: 3.10
Classifier: Programming Language :: Python :: 3.11
Classifier: Programming Language :: C++
Classifier: Operating System :: OS Independent
Classifier: Operating System :: Microsoft :: Windows
Classifier: Operating System :: POSIX :: Linux
Classifier: Operating System :: MacOS
Requires-Python: >=3.7
Requires-Dist: pybind11>=2.6.0
Provides-Extra: test
Requires-Dist: pytest>=6.0; extra == "test"
Requires-Dist: hypothesis>=6.0; extra == "test"
Provides-Extra: dev
Requires-Dist: pytest>=6.0; extra == "dev"
Requires-Dist: hypothesis>=6.0; extra == "dev"
Requires-Dist: cmake>=3.16; extra == "dev"
Dynamic: author
Dynamic: home-page
Dynamic: requires-python
